MANIFEST.in
README.md
setup.cfg
setup.py
MongoIngestorS3.egg-info/PKG-INFO
MongoIngestorS3.egg-info/SOURCES.txt
MongoIngestorS3.egg-info/dependency_links.txt
MongoIngestorS3.egg-info/requires.txt
MongoIngestorS3.egg-info/top_level.txt
src/__init__.py
src/config.py
src/connectors/__init__.py
src/connectors/aws_connector.py
src/connectors/mongo_connector.py
src/core/__init__.py
src/core/aws_manager.py
src/core/mongo_manager.py
src/serializers/__init__.py
src/serializers/csv_serializer.py
src/serializers/json_serializer.py
src/serializers/serializer.py
src/serializers/serializer_factory.py